aws_paramstore_py/__init__.py
aws_paramstore_py/main.py
aws_paramstore_py-0.1.0.dist-info/DESCRIPTION.rst
aws_paramstore_py-0.1.0.dist-info/METADATA
aws_paramstore_py-0.1.0.dist-info/RECORD
aws_paramstore_py-0.1.0.dist-info/WHEEL
aws_paramstore_py-0.1.0.dist-info/entry_points.txt
aws_paramstore_py-0.1.0.dist-info/metadata.json
aws_paramstore_py-0.1.0.dist-info/top_level.txt
