Metadata-Version: 2.0
Name: aws-paramstore-py
Version: 0.1.0
Summary: Query params from AWS System Manager Parameter Store
Home-page: https://github.com/akirakoyasu/aws-paramstore-py
Author: Akira Koyasu
Author-email: mail@akirakoyasu.net
License: UNKNOWN
Keywords: aws parameter store
Platform: UNKNOWN
Classifier: Development Status :: 4 - Beta
Classifier: Intended Audience :: Developers
Classifier: Topic :: Software Development :: Libraries :: Python Modules
Classifier: License :: OSI Approved :: MIT License
Classifier: Programming Language :: Python :: 3
Classifier: Programming Language :: Python :: 3.4
Classifier: Programming Language :: Python :: 3.5
Classifier: Programming Language :: Python :: 3.6
Requires-Python: >=3
Requires-Dist: boto3
